postnormalism/VERSION
postnormalism/__init__.py
postnormalism/core.py
postnormalism/utils.py
postnormalism/schema/__init__.py
postnormalism/schema/database.py
postnormalism/schema/database_item.py
postnormalism/schema/domain.py
postnormalism/schema/function.py
postnormalism/schema/migrations.py
postnormalism/schema/schema.py
postnormalism/schema/table.py
postnormalism/schema/trigger.py
postnormalism/schema/view.py
postnormalism-0.0.7.dist-info/LICENSE
postnormalism-0.0.7.dist-info/METADATA
postnormalism-0.0.7.dist-info/WHEEL
postnormalism-0.0.7.dist-info/top_level.txt
postnormalism-0.0.7.dist-info/RECORD
