Metadata-Version: 2.1
Name: postnormalism
Version: 0.0.7
Summary: Postnormalism is Not an Object Relational Mapper (NORM) it is a lightweight and simple-to-use Python library for managing PostgreSQL database schemas. It provides an easy way to define tables and functions, organize schema items, and create them in a database with a specified load order.
Author-email: Zac Miller <zac@informatical.info>
Maintainer-email: Zac Miller <zac@informatical.info>
License: MIT License
Project-URL: Homepage, https://github.com/jzmiller1/postnormalism
Project-URL: Bug Tracker, https://github.com/jzmiller1/postnormalism/issues
Project-URL: Repository, https://github.com/jzmiller1/postnormalism.git
Project-URL: History, https://github.com/jzmiller1/postnormalism/blob/master/HISTORY.md
Keywords: python,postgresql,schema
Classifier: Programming Language :: Python :: 3
Classifier: License :: OSI Approved :: MIT License
Classifier: Operating System :: OS Independent
Classifier: Development Status :: 2 - Pre-Alpha
Classifier: Intended Audience :: Developers
Requires-Python: >=3.11
License-File: LICENSE
